{
  "accuracy": 0.4721,
  "f1_macro": 0.3095,
  "draw_recall": 0.0,
  "log_loss": 1.0179,
  "brier_score": 0.6102,
  "calibration_error": 0.0486,
  "roc_auc_ovr_macro": 0.6091,
  "majority_baseline_accuracy": 0.4623,
  "market_baseline_accuracy": 0.4721,
  "market_baseline_log_loss": 1.0179,
  "market_baseline_brier_score": 0.6102,
  "market_accuracy_delta": 0.0,
  "market_log_loss_delta": 0.0,
  "market_brier_delta": 0.0,
  "roi_pct": -17.27,
  "profit_units": -20.9,
  "bets_placed": 121,
  "bet_win_rate": 0.1901,
  "closing_line_value_pct": 0.34,
  "market_blend_weight": 1.0,
  "class_distribution_train": {
    "0": 0.3081,
    "1": 0.2563,
    "2": 0.4357
  },
  "n_train": 3551,
  "n_test": 305,
  "split": "last_full_season",
  "holdout_season": "2025-26",
  "train_end": "2025-05-17",
  "test_start": "2025-08-15",
  "test_end": "2026-05-17",
  "feature_cols": [
    "HomeGoals_Avg_L5",
    "HomeConceded_Avg_L5",
    "HomeShots_Avg_L5",
    "HomeSOT_Avg_L5",
    "HomeWinRate_L10",
    "HomeMomentum_L3",
    "HomeRestDays",
    "HomeVenueGoals_Avg_L5",
    "HomeVenueConceded_Avg_L5",
    "HomeVenueWinRate_L10",
    "HomeElo",
    "AwayGoals_Avg_L5",
    "AwayConceded_Avg_L5",
    "AwayShots_Avg_L5",
    "AwaySOT_Avg_L5",
    "AwayWinRate_L10",
    "AwayMomentum_L3",
    "AwayRestDays",
    "AwayVenueGoals_Avg_L5",
    "AwayVenueConceded_Avg_L5",
    "AwayVenueWinRate_L10",
    "AwayElo",
    "EloDiff",
    "ImpliedProb_HomeWin",
    "ImpliedProb_Draw",
    "ImpliedProb_AwayWin",
    "MarketHomeEdge",
    "MarketAwayEdge",
    "MarketEntropy",
    "HomeCopaCongestion",
    "AwayCopaCongestion"
  ],
  "walk_forward": [
    {
      "season": "2018-19",
      "matches": 380,
      "accuracy": 0.4816,
      "market_accuracy": 0.4842,
      "log_loss": 1.0577,
      "market_log_loss": 1.0033
    },
    {
      "season": "2019-20",
      "matches": 279,
      "accuracy": 0.4516,
      "market_accuracy": 0.5233,
      "log_loss": 1.0661,
      "market_log_loss": 0.9913
    },
    {
      "season": "2020-21",
      "matches": 380,
      "accuracy": 0.4684,
      "market_accuracy": 0.5105,
      "log_loss": 1.0566,
      "market_log_loss": 1.0003
    },
    {
      "season": "2021-22",
      "matches": 380,
      "accuracy": 0.4974,
      "market_accuracy": 0.5,
      "log_loss": 1.0192,
      "market_log_loss": 1.0003
    },
    {
      "season": "2022-23",
      "matches": 380,
      "accuracy": 0.5132,
      "market_accuracy": 0.55,
      "log_loss": 0.9906,
      "market_log_loss": 0.9696
    },
    {
      "season": "2023-24",
      "matches": 306,
      "accuracy": 0.4444,
      "market_accuracy": 0.5065,
      "log_loss": 1.0743,
      "market_log_loss": 1.0149
    },
    {
      "season": "2024-25",
      "matches": 306,
      "accuracy": 0.5327,
      "market_accuracy": 0.5425,
      "log_loss": 0.9997,
      "market_log_loss": 0.9585
    },
    {
      "season": "2025-26",
      "matches": 305,
      "accuracy": 0.4689,
      "market_accuracy": 0.4721,
      "log_loss": 1.0431,
      "market_log_loss": 1.0179
    }
  ]
}